odoo/addons/partner_tz/README.rst
odoo/addons/partner_tz/__init__.py
odoo/addons/partner_tz/__manifest__.py
odoo/addons/partner_tz/i18n/it.po
odoo/addons/partner_tz/i18n/partner_tz.pot
odoo/addons/partner_tz/readme/CONTRIBUTORS.md
odoo/addons/partner_tz/readme/CREDITS.md
odoo/addons/partner_tz/readme/DESCRIPTION.md
odoo/addons/partner_tz/readme/ROADMAP.md
odoo/addons/partner_tz/static/description/icon.png
odoo/addons/partner_tz/static/description/index.html
odoo/addons/partner_tz/tests/__init__.py
odoo/addons/partner_tz/tests/common.py
odoo/addons/partner_tz/tests/test_tz.py
odoo/addons/partner_tz/tools/__init__.py
odoo/addons/partner_tz/tools/tz_utils.py
odoo/addons/partner_tz/views/res_partner.xml
odoo_addon_partner_tz-18.0.1.0.1.dist-info/METADATA
odoo_addon_partner_tz-18.0.1.0.1.dist-info/WHEEL
odoo_addon_partner_tz-18.0.1.0.1.dist-info/top_level.txt
odoo_addon_partner_tz-18.0.1.0.1.dist-info/RECORD
